hina/__init__.py
hina/app/__init__.py
hina/app/api/__init__.py
hina/app/api/api.py
hina/app/api/utils.py
hina/construction/__init__.py
hina/construction/network_construct.py
hina/data/__init__.py
hina/dyad/__init__.py
hina/dyad/significant_edges.py
hina/individual/__init__.py
hina/individual/diversity.py
hina/individual/quantity.py
hina/mesoscale/__init__.py
hina/mesoscale/clustering.py
hina/utils/__init__.py
hina/utils/graph_tools.py
hina/visualization/__init__.py
hina/visualization/network_visualization.py
hina-0.7.10.dist-info/licenses/LICENSE.txt
hina-0.7.10.dist-info/METADATA
hina-0.7.10.dist-info/WHEEL
hina-0.7.10.dist-info/top_level.txt
hina-0.7.10.dist-info/RECORD
