Metadata-Version: 2.4
Name: hina
Version: 0.7.10
Summary: Heterogenous Interaction Network Analysis in Python
Home-page: https://hina.readthedocs.io/en/latest/index.html
Author: Shihui Feng, Baiyue He, Alec Kirkley
Author-email: shihuife@hku.hk, baiyue.he@connect.hku.hk, akirkley@hku.hk
License: The MIT License
Project-URL: Documentation, https://hina.readthedocs.io/en/latest/index.html
Project-URL: Source, https://hina.readthedocs.io/en/latest/index.html
Requires-Python: >=3.10
License-File: LICENSE.txt
Requires-Dist: numpy>=1.24
Requires-Dist: pandas>=2.2
Requires-Dist: scipy>=1.10
Requires-Dist: python-multipart>=0.0.18
Requires-Dist: dash<=3.0.0
Requires-Dist: dash-cytoscape>=1.0.2
Requires-Dist: matplotlib>=3.8.4
Requires-Dist: networkx>=3.0
Requires-Dist: fastapi>=0.111.0
Requires-Dist: uvicorn>=0.30.0
Requires-Dist: openpyxl>=3.1.5
Provides-Extra: dev
Requires-Dist: pytest; extra == "dev"
Requires-Dist: pytest-cov; extra == "dev"
Requires-Dist: pytest-html; extra == "dev"
Dynamic: author
Dynamic: author-email
Dynamic: description
Dynamic: description-content-type
Dynamic: home-page
Dynamic: license
Dynamic: license-file
Dynamic: project-url
Dynamic: provides-extra
Dynamic: requires-dist
Dynamic: requires-python
Dynamic: summary
